simba_chem/__init__.py
simba_chem/analysis.py
simba_chem/calculus.py
simba_chem/core.py
simba_chem/gui_server.py
simba_chem/helpers.py
simba_chem/model_classes.py
simba_chem/self_shielding.py
simba_chem/data/__init__.py
simba_chem/data/chemnet_example_keyte2023.dat
simba_chem/data/data_selfshielding_co.dat
simba_chem/data/data_selfshielding_n2.dat
simba_chem/gui/jsconfig.json
simba_chem/gui/next-env.d.ts
simba_chem/gui/next.config.mjs
simba_chem/gui/package-lock.json
simba_chem/gui/package.json
simba_chem/gui/postcss.config.js
simba_chem/gui/postcss.config.mjs
simba_chem/gui/tailwind.config.js
simba_chem/gui/tsconfig.json
simba_chem/gui/public/file.svg
simba_chem/gui/public/globe.svg
simba_chem/gui/public/lukenet_logo.png
simba_chem/gui/public/next.svg
simba_chem/gui/public/vercel.svg
simba_chem/gui/public/window.svg
simba_chem/gui/src/app/favicon.ico
simba_chem/gui/src/app/globals.css
simba_chem/gui/src/app/layout.js
simba_chem/gui/src/app/page.js
simba_chem/gui/src/app/api/check-progress/route.js
simba_chem/gui/src/app/api/run-solver/route.js
simba_chem/gui/src/app/fonts/GeistMonoVF.woff
simba_chem/gui/src/app/fonts/GeistVF.woff
simba_chem/gui/src/components/PathwayDiagram.js
simba_chem/gui/src/components/ui/card.jsx
simba_chem/gui/src/lib/utils.js
simba_chem-1.0.2.dist-info/licenses/LICENSE
simba_chem-1.0.2.dist-info/METADATA
simba_chem-1.0.2.dist-info/WHEEL
simba_chem-1.0.2.dist-info/entry_points.txt
simba_chem-1.0.2.dist-info/top_level.txt
simba_chem-1.0.2.dist-info/RECORD
