Metadata-Version: 2.4
Name: simba_chem
Version: 1.0.2
Summary: Astrophysical Chemical Network Solver
Author: Luke Keyte
Requires-Python: >=3.8
License-File: LICENSE
Requires-Dist: numpy
Requires-Dist: scipy
Requires-Dist: matplotlib
Requires-Dist: numba
Requires-Dist: tqdm
Requires-Dist: pandas
Dynamic: license-file
